ChiantiPy/__init__.py
ChiantiPy/__init__gh.py
ChiantiPy/__init__kpd.py
ChiantiPy/__init_kpd__.py
ChiantiPy/version.py
ChiantiPy/Gui/__init__.py
ChiantiPy/Gui/gui_cl/__init__.py
ChiantiPy/Gui/gui_cl/gui.py
ChiantiPy/Gui/gui_qt5/__init__.py
ChiantiPy/Gui/gui_qt5/gui.py
ChiantiPy/Gui/gui_qt5/ui.py
ChiantiPy/base/_IonTrails.py
ChiantiPy/base/_IoneqOne.py
ChiantiPy/base/_SpecTrails.py
ChiantiPy/base/__init__.py
ChiantiPy/core/Bunch.py
ChiantiPy/core/Continuum.py
ChiantiPy/core/Ion.py
ChiantiPy/core/Ioneq.py
ChiantiPy/core/IpyMspectrum.py
ChiantiPy/core/MradLoss.py
ChiantiPy/core/Mspectrum.py
ChiantiPy/core/RadLoss.py
ChiantiPy/core/Redux.py
ChiantiPy/core/Spectrum.py
ChiantiPy/core/_IonNew.py
ChiantiPy/core/__init__.py
ChiantiPy/core/ioneq_pylint.txt
ChiantiPy/core/tests/__init__.py
ChiantiPy/core/tests/test_Continuum.py
ChiantiPy/core/tests/test_Ion.py
ChiantiPy/core/tests/test_Ioneq.py
ChiantiPy/core/tests/test_Spectrum.py
ChiantiPy/core/tests/test_spectrum_api.py
ChiantiPy/fortranformat/COPYING.txt
ChiantiPy/fortranformat/FortranRecordReader.py
ChiantiPy/fortranformat/FortranRecordWriter.py
ChiantiPy/fortranformat/__init__.py
ChiantiPy/fortranformat/_edit_descriptors.py
ChiantiPy/fortranformat/_exceptions.py
ChiantiPy/fortranformat/_input.py
ChiantiPy/fortranformat/_lexer.py
ChiantiPy/fortranformat/_misc.py
ChiantiPy/fortranformat/_output.py
ChiantiPy/fortranformat/_parser.py
ChiantiPy/fortranformat/config.py
ChiantiPy/model/Maker.py
ChiantiPy/model/MakerD.py
ChiantiPy/model/MakerMc.py
ChiantiPy/model/__init__.py
ChiantiPy/model/__init__just_Maker.py
ChiantiPy/tests/__init__.py
ChiantiPy/tests/setup_package.py
ChiantiPy/tools/__init__.py
ChiantiPy/tools/archival.py
ChiantiPy/tools/constants.py
ChiantiPy/tools/data.py
ChiantiPy/tools/filters.py
ChiantiPy/tools/io.py
ChiantiPy/tools/mputil.py
ChiantiPy/tools/sources.py
ChiantiPy/tools/util.py
ChiantiPy-0.15.2.dist-info/ChiantiPy/__init__.py
ChiantiPy-0.15.2.dist-info/ChiantiPy/__init__.pyc
ChiantiPy-0.15.2.dist-info/ChiantiPy/__init__gh.py
ChiantiPy-0.15.2.dist-info/ChiantiPy/__init__kpd.py
ChiantiPy-0.15.2.dist-info/ChiantiPy/__init_kpd__.py
ChiantiPy-0.15.2.dist-info/ChiantiPy/version.py
ChiantiPy-0.15.2.dist-info/ChiantiPy/Gui/__init__.py
ChiantiPy-0.15.2.dist-info/ChiantiPy/Gui/gui_cl/__init__.py
ChiantiPy-0.15.2.dist-info/ChiantiPy/Gui/gui_cl/gui.py
ChiantiPy-0.15.2.dist-info/ChiantiPy/Gui/gui_qt6/__init__.py
ChiantiPy-0.15.2.dist-info/ChiantiPy/Gui/gui_qt6/gui.py
ChiantiPy-0.15.2.dist-info/ChiantiPy/Gui/gui_qt6/ui.py
ChiantiPy-0.15.2.dist-info/ChiantiPy/__pycache__/__init__.cpython-310.pyc
ChiantiPy-0.15.2.dist-info/ChiantiPy/__pycache__/__init__.cpython-311.pyc
ChiantiPy-0.15.2.dist-info/ChiantiPy/__pycache__/__init__.cpython-312.pyc
ChiantiPy-0.15.2.dist-info/ChiantiPy/__pycache__/__init__.cpython-313.pyc
ChiantiPy-0.15.2.dist-info/ChiantiPy/__pycache__/__init__.cpython-34.pyc
ChiantiPy-0.15.2.dist-info/ChiantiPy/__pycache__/__init__.cpython-36.pyc
ChiantiPy-0.15.2.dist-info/ChiantiPy/__pycache__/__init__.cpython-38.pyc
ChiantiPy-0.15.2.dist-info/ChiantiPy/__pycache__/__init__.cpython-39.pyc
ChiantiPy-0.15.2.dist-info/ChiantiPy/__pycache__/_astropy_init.cpython-34.pyc
ChiantiPy-0.15.2.dist-info/ChiantiPy/__pycache__/archival.cpython-34.pyc
ChiantiPy-0.15.2.dist-info/ChiantiPy/__pycache__/conftest.cpython-36.pyc
ChiantiPy-0.15.2.dist-info/ChiantiPy/__pycache__/constants.cpython-34.pyc
ChiantiPy-0.15.2.dist-info/ChiantiPy/__pycache__/data.cpython-34.pyc
ChiantiPy-0.15.2.dist-info/ChiantiPy/__pycache__/filters.cpython-34.pyc
ChiantiPy-0.15.2.dist-info/ChiantiPy/__pycache__/io.cpython-34.pyc
ChiantiPy-0.15.2.dist-info/ChiantiPy/__pycache__/ipymputil.cpython-34.pyc
ChiantiPy-0.15.2.dist-info/ChiantiPy/__pycache__/mputil.cpython-34.pyc
ChiantiPy-0.15.2.dist-info/ChiantiPy/__pycache__/static_version.cpython-34.pyc
ChiantiPy-0.15.2.dist-info/ChiantiPy/__pycache__/static_version.cpython-36.pyc
ChiantiPy-0.15.2.dist-info/ChiantiPy/__pycache__/util.cpython-34.pyc
ChiantiPy-0.15.2.dist-info/ChiantiPy/__pycache__/version.cpython-310.pyc
ChiantiPy-0.15.2.dist-info/ChiantiPy/__pycache__/version.cpython-311.pyc
ChiantiPy-0.15.2.dist-info/ChiantiPy/__pycache__/version.cpython-312.pyc
ChiantiPy-0.15.2.dist-info/ChiantiPy/__pycache__/version.cpython-313.pyc
ChiantiPy-0.15.2.dist-info/ChiantiPy/__pycache__/version.cpython-34.pyc
ChiantiPy-0.15.2.dist-info/ChiantiPy/__pycache__/version.cpython-36.pyc
ChiantiPy-0.15.2.dist-info/ChiantiPy/__pycache__/version.cpython-38.pyc
ChiantiPy-0.15.2.dist-info/ChiantiPy/__pycache__/version.cpython-39.pyc
ChiantiPy-0.15.2.dist-info/ChiantiPy/__pycache__/version_gh.cpython-36.pyc
ChiantiPy-0.15.2.dist-info/ChiantiPy/base/_IonTrails.py
ChiantiPy-0.15.2.dist-info/ChiantiPy/base/_IonTrails.pyc
ChiantiPy-0.15.2.dist-info/ChiantiPy/base/_IoneqOne.py
ChiantiPy-0.15.2.dist-info/ChiantiPy/base/_SpecTrails.py
ChiantiPy-0.15.2.dist-info/ChiantiPy/base/_SpecTrails.pyc
ChiantiPy-0.15.2.dist-info/ChiantiPy/base/__init__.py
ChiantiPy-0.15.2.dist-info/ChiantiPy/base/__init__.pyc
ChiantiPy-0.15.2.dist-info/ChiantiPy/base/__pycache__/_IonTrails.cpython-310.pyc
ChiantiPy-0.15.2.dist-info/ChiantiPy/base/__pycache__/_IonTrails.cpython-311.pyc
ChiantiPy-0.15.2.dist-info/ChiantiPy/base/__pycache__/_IonTrails.cpython-312.pyc
ChiantiPy-0.15.2.dist-info/ChiantiPy/base/__pycache__/_IonTrails.cpython-313.pyc
ChiantiPy-0.15.2.dist-info/ChiantiPy/base/__pycache__/_IonTrails.cpython-34.pyc
ChiantiPy-0.15.2.dist-info/ChiantiPy/base/__pycache__/_IonTrails.cpython-36.pyc
ChiantiPy-0.15.2.dist-info/ChiantiPy/base/__pycache__/_IonTrails.cpython-38.pyc
ChiantiPy-0.15.2.dist-info/ChiantiPy/base/__pycache__/_IoneqOne.cpython-310.pyc
ChiantiPy-0.15.2.dist-info/ChiantiPy/base/__pycache__/_IoneqOne.cpython-311.pyc
ChiantiPy-0.15.2.dist-info/ChiantiPy/base/__pycache__/_IoneqOne.cpython-312.pyc
ChiantiPy-0.15.2.dist-info/ChiantiPy/base/__pycache__/_IoneqOne.cpython-313.pyc
ChiantiPy-0.15.2.dist-info/ChiantiPy/base/__pycache__/_IoneqOne.cpython-36.pyc
