Metadata-Version: 2.2
Name: ChiantiPy
Version: 0.15.2
Summary: a Python interface to the CHIANTI atomic database for astrophysical spectroscopy
Home-page: https://github.com/chianti-atomic/ChiantiPy
Author: Ken Dere
Author-email: kdere@gmu.edu
License: ISC
Classifier: Development Status :: 3 - Alpha
Classifier: Environment :: Console
Classifier: Intended Audience :: Science/Research
Classifier: Intended Audience :: End Users/Desktop
Classifier: License :: OSI Approved :: ISC License (ISCL)
Classifier: Operating System :: POSIX :: Linux
Classifier: Programming Language :: Python :: 3
Classifier: Topic :: Scientific/Engineering :: Astronomy
Classifier: Topic :: Scientific/Engineering :: Physics
Dynamic: author
Dynamic: author-email
Dynamic: classifier
Dynamic: description
Dynamic: home-page
Dynamic: summary
